wiliot_core/__init__.py
wiliot_core/requirements.txt
wiliot_core/version.py
wiliot_core/local_gateway/__init__.py
wiliot_core/local_gateway/continuous_listener.py
wiliot_core/local_gateway/custom_energy_pattern.py
wiliot_core/local_gateway/local_gateway_core.py
wiliot_core/local_gateway/examples/__init__.py
wiliot_core/local_gateway/examples/dual_gw_example.py
wiliot_core/local_gateway/examples/local_gateway_basic_example.py
wiliot_core/local_gateway/local_gateway_versions/4.1.4_app.zip
wiliot_core/local_gateway/local_gateway_versions/4.1.4_sd_bl_gw_app.zip
wiliot_core/local_gateway/local_gateway_versions/4.2.0_app.zip
wiliot_core/local_gateway/local_gateway_versions/4.2.0_sd_bl_gw_app.zip
wiliot_core/local_gateway/local_gateway_versions/4.3.3_app.zip
wiliot_core/local_gateway/local_gateway_versions/4.3.3_sd_bl_gw_app.zip
wiliot_core/local_gateway/local_gateway_versions/4.3.4_app.zip
wiliot_core/local_gateway/local_gateway_versions/4.3.4_sd_bl_gw_app.zip
wiliot_core/local_gateway/local_gateway_versions/4.3.6_app.zip
wiliot_core/local_gateway/local_gateway_versions/4.3.6_sd_bl_gw_app.zip
wiliot_core/local_gateway/local_gateway_versions/4.4.0_app.zip
wiliot_core/local_gateway/local_gateway_versions/4.4.0_sd_bl_gw_app.zip
wiliot_core/local_gateway/local_gateway_versions/4.4.3_app.zip
wiliot_core/local_gateway/local_gateway_versions/4.4.3_sd_bl_gw_app.zip
wiliot_core/local_gateway/local_gateway_versions/4.4.9_app.zip
wiliot_core/local_gateway/local_gateway_versions/4.4.9_sd_bl_gw_app.zip
wiliot_core/local_gateway/local_gateway_versions/4.5.6_app.zip
wiliot_core/local_gateway/local_gateway_versions/4.5.6_sd_bl_gw_app.zip
wiliot_core/local_gateway/local_gateway_versions/__init__.py
wiliot_core/local_gateway/local_gateway_versions/wifi_4.1.4.hex
wiliot_core/local_gateway/local_gateway_versions/wifi_4.2.0.hex
wiliot_core/local_gateway/local_gateway_versions/wifi_4.3.3.hex
wiliot_core/local_gateway/local_gateway_versions/wifi_4.3.4.hex
wiliot_core-5.13.1.dist-info/LICENSE
wiliot_core-5.13.1.dist-info/METADATA
wiliot_core-5.13.1.dist-info/WHEEL
wiliot_core-5.13.1.dist-info/top_level.txt
wiliot_core-5.13.1.dist-info/RECORD
