Metadata-Version: 2.1
Name: wiliot_core
Version: 5.13.1
Summary: A library for interacting with Wiliot's private core functions
Home-page: 
Author: Wiliot
Author-email: support@wiliot.com
License: MIT
Project-URL: Bug Tracker, https://WILIOT-ZENDESK-URL
Classifier: Programming Language :: Python :: 3
Classifier: License :: OSI Approved :: MIT License
Classifier: Operating System :: OS Independent
Requires-Python: >=3.6
License-File: LICENSE
Requires-Dist: setuptools-scm
Requires-Dist: pyserial
Requires-Dist: pandas
Requires-Dist: appdirs
Requires-Dist: numpy (<2,>=1.20.0) ; python_version < "3.11"
Requires-Dist: setuptools-scm (==8.1.0) ; python_version >= "3.10" and python_version < "3.11"
Requires-Dist: pyserial (==3.5) ; python_version >= "3.10" and python_version < "3.11"
Requires-Dist: pandas (==1.5.3) ; python_version >= "3.10" and python_version < "3.11"
Requires-Dist: numpy (==1.24.4) ; python_version >= "3.10" and python_version < "3.11"
Requires-Dist: appdirs (==1.4.4) ; python_version >= "3.10" and python_version < "3.11"
Requires-Dist: numpy (>2) ; python_version >= "3.11"
Requires-Dist: pc-ble-driver-py ; sys_platform != "linux" and python_version < "3.11"
Requires-Dist: nrfutil ; sys_platform != "linux" and python_version < "3.11"
Requires-Dist: pc-ble-driver-py (==0.11.4) ; sys_platform != "linux" and python_version >= "3.10" and python_version < "3.11"
Requires-Dist: nrfutil (==5.2.0) ; sys_platform != "linux" and python_version >= "3.10" and python_version < "3.11"
